uplot/__init__.py
uplot/_version.py
uplot/core.py
uplot/old.py
uplot/options.py
uplot/quick.py
uplot/version.py
uplot/_include/mpl_line_styles.yml
uplot/_include/mpl_markers.yml
uplot/_include/uplot.mplstyle
uplot-0.1.61.dist-info/LICENSE.md
uplot-0.1.61.dist-info/METADATA
uplot-0.1.61.dist-info/WHEEL
uplot-0.1.61.dist-info/top_level.txt
uplot-0.1.61.dist-info/zip-safe
uplot-0.1.61.dist-info/RECORD
