Metadata-Version: 2.1
Name: uplot
Version: 0.1.61
Summary: A toolkit for executing and analyzing machine learning classification
Home-page: https://www.lockhartlab.org
Author: C. Lockhart
Author-email: chris@lockhartlab.org
License: UNKNOWN
Platform: UNKNOWN
Requires-Dist: codecov
Requires-Dist: coverage
Requires-Dist: hypothesis
Requires-Dist: IPython
Requires-Dist: izzy
Requires-Dist: matplotlib
Requires-Dist: numpy
Requires-Dist: pandas
Requires-Dist: plotnine
Requires-Dist: pyyaml
Requires-Dist: typelike
